modernize.py
libmodernize/__init__.py
libmodernize/main.py
libmodernize/fixes/__init__.py
libmodernize/fixes/fix_basestring.py
libmodernize/fixes/fix_classic_division.py
libmodernize/fixes/fix_dict_six.py
libmodernize/fixes/fix_file.py
libmodernize/fixes/fix_filter.py
libmodernize/fixes/fix_import.py
libmodernize/fixes/fix_imports_six.py
libmodernize/fixes/fix_input_six.py
libmodernize/fixes/fix_int_long_tuple.py
libmodernize/fixes/fix_itertools_imports_six.py
libmodernize/fixes/fix_itertools_six.py
libmodernize/fixes/fix_map.py
libmodernize/fixes/fix_metaclass.py
libmodernize/fixes/fix_next.py
libmodernize/fixes/fix_open.py
libmodernize/fixes/fix_print.py
libmodernize/fixes/fix_raise.py
libmodernize/fixes/fix_raise_six.py
libmodernize/fixes/fix_unichr.py
libmodernize/fixes/fix_unicode.py
libmodernize/fixes/fix_unicode_future.py
libmodernize/fixes/fix_unicode_type.py
libmodernize/fixes/fix_urllib_six.py
libmodernize/fixes/fix_xrange_six.py
libmodernize/fixes/fix_zip.py
modernize-0.7.dist-info/LICENSE
modernize-0.7.dist-info/METADATA
modernize-0.7.dist-info/WHEEL
modernize-0.7.dist-info/entry_points.txt
modernize-0.7.dist-info/top_level.txt
modernize-0.7.dist-info/RECORD
