Metadata-Version: 1.1
Name: modernize
Version: 0.7
Summary: A hack on top of 2to3 for modernizing code for hybrid codebases.
Home-page: https://github.com/python-modernize/python-modernize
Author: Armin Ronacher
Author-email: armin.ronacher@active-4.com
License: UNKNOWN
Platform: UNKNOWN
Classifier: License :: OSI Approved :: BSD License
Classifier: Programming Language :: Python
Classifier: Programming Language :: Python :: 2.7
Classifier: Programming Language :: Python :: 2.6
Classifier: Programming Language :: Python :: 3
